{"colors":[{"code":"M","rgb":[163,53,238],"label":"Magenta"},{"code":"L","rgb":[195,176,145],"label":"Lore text"},{"code":"G","rgb":[41,225,38],"label":"Green"},{"code":"R","rgb":[252,86,70],"label":"Red"},{"code":"B","rgb":[51,167,255],"label":"Blue"},{"code":"Y","rgb":[247,252,52],"label":"Yellow"},{"code":"H","rgb":[251,170,41],"label":"Highlight"},{"code":"C","rgb":[31,224,202],"label":"Cyan"},{"code":"K","rgb":[251,170,41],"label":"Header for Concepts"},{"code":"I","rgb":[247,252,52],"label":"Highlights for Concepts"},{"code":"T","rgb":[255,255,255],"label":"Text"},{"code":"t","rgb":[198,198,198],"label":"Concept tooltip texts are wrapped in this when shown in the UI"},{"code":"E","rgb":[135,255,207],"label":"Standard green"},{"code":"S","rgb":[228,156,42],"label":"Subtitle highlight (light green in this case)"},{"code":"W","rgb":[255,255,255],"label":"White"},{"code":"P","rgb":[225,110,110],"label":"Pink"},{"code":"V","rgb":[76,138,113],"label":"Dark Green"},{"code":"g","rgb":[128,128,128],"label":"Grey"},{"code":"_","rgb":[255,0,255],"label":"_ Placeholder magenta"},{"code":"U","rgb":[204,179,255],"label":"Mauve"},{"code":"c","rgb":[60,208,146],"label":"c"},{"code":"v","rgb":[139,174,162],"label":"v"},{"code":"d","rgb":[255,221,122],"label":"d"},{"code":"r","rgb":[163,130,255],"label":"r"},{"code":"l","rgb":[178,236,104],"label":"l"},{"code":"0","rgb":[31,224,202],"label":"0"},{"code":"1","rgb":[51,167,255],"label":"1"},{"code":"2","rgb":[163,53,238],"label":"2"},{"code":"3","rgb":[251,170,41],"label":"3"}],"icons":["amenities","amenities_no_happiness","anglers","anglers_corporate","anomaly","anomaly_level","aptitude","aquatic","archaeoengineers","archaeology","archivism","arcology_project","army_power","army_ship","arrow_down","arrow_up","assembly_slag","assign_envoy","astral_rift","astrometeorology","astrometeorology_hive","astrometeorology_machine","astrometeorology_megacorp","attunement","augmentation_bazaars","authoritarian","automate_research","awareness","backspace","barbaric_despoiler","basic_resources","basic_resources_alloys","beastmasters","become_the_crisis","beta","blocker","budding","building","bulwark","call_favor","camera_rotate","camera_zoom_in","camera_zoom_out","casus_belli_target","catalytic_processing","catalytic_processing_corporate","catalytic_processing_hive","catalytic_processing_machine","chosen","civil_education","clear_blocker","cloning","cognitive_node","colonies","colonizable","colony","colony_ship","colossus_project","colossus_ship","comma","commander","community_in_breach","construction_ship","construction_ship_map","contacts","cordyceptic_drones","corporate_authority","corporate_beastmasters","corporate_chosen","corporate_crowdsourcing","corporate_galactic_curators","corporate_galvanic_symbiosis","corporate_genetic_identification","corporate_guided_sapience","corporate_world_forgers","council","crime","crowdsourcing","crucible_community","crusader_spirit","crusader_spirit_corporate","ctrl","dark_consortium","dark_consortium_corporate","databank","databank_all","databank_colony","databank_conquest","databank_development","databank_empire","databank_exploration","databank_interface","databank_resource","death_cult","death_cult_corporate","decision","defense_army","del","detox","dimensional_worship","dimensional_worship_corporate","diplo_weight","discoveries","district","districtadd","domestication","dot","dot_green","dot_red","eager_explorers","economy","egalitarian","empire","empire_sprawl","end","energy","engineered_evolution","engineering","enigmatic_engineering","enmity","entropy_conduit","entropy_drinkers","entropy_drinkers_corporate","entropy_drinkers_hive_mind","entropy_drinkers_machine","environmental_architects","environmental_architects_hive","environmental_architects_machine","environmental_architects_megacorp","envoy","escape","existential_iteroparity","exotic_gases","exotic_metabolism","exploration_protocol","f1","f10","f2","f3","f4","f5","f6","f7","f8","f9","favor","federation","firstcontact","fleet_management","fleet_size","fleet_status","fleet_template_size","focus_conquest","focus_conquest_yellow","focus_core","focus_development","focus_exploration","frozen_resolution","galactic_curators","galactic_hyperthermia","galactic_wonders","galaxy_view","galcom_endsession","galvanic_symbiosis","gaseous_byproducts","genetic_identification","genetic_material","growth_node","guided_sapience","happiness","heroic_past","heroic_past_corporate","heroic_past_hive","heroic_past_machine","hive_aerospace_adaptation","hive_authority","hive_beastmasters","hive_bodysnatcher","hive_chosen","hive_familiar_face","hive_galactic_curators","hive_galvanic_symbiosis","hive_guided_sapience","hive_natural_design","hive_scorched_earth","hive_shared_genetics","hive_superstitious_beliefs","hive_world_forgers","hive_worlds","home","housing","hydrocentric","hyperspace_specialty","hyperspace_specialty_corporate","hyperspace_specialty_hive","hyperspace_specialty_machine","idyllic_bloom","idyllic_bloom_hive","incubator","infernal","influence","inorganic_breath","intel_encryption","interface","invasive_species","jinxed","job","job_calculator","job_enforcer","job_unemployment","kp_minus","kp_plus","leader","leader_skill","leaders","legion_node","lithoid","lithoids_dlc","lord_of_war","loyalty","machine_authority","machine_beastmasters","machine_chosen","machine_diplomatic_protocols","machine_galactic_curators","machine_galvanic_symbiosis","machine_guided_sapience","machine_obsessional_directive","machine_stalwart_network","machine_superstitious_beliefs","machine_tactical_algorithms","machine_world_forgers","machine_worlds","mandarin_advisor","market","master_builders","master_crafters","master_crafters_corporate","materialist","mechromancy","megastructure","memorialist","memorialist_hive","memorialist_machine","memory_vault","memory_vault_hive","memory_vault_machine","memory_vault_megacorp","militarist","military_power","military_power_boss","military_power_ultra_boss","military_ship","mind_over_matter","minerals","mining_station","minus_plus","modifier_unknown","modularity","mouse4","mouse5","mutation","nanotech","natural_design","navy_size","nihilistic_acquisition","noclass","noxious","numeral_1","numeral_10","numeral_2","numeral_3","numeral_4","numeral_5","numeral_6","numeral_7","numeral_8","numeral_9","official","opinion","oppressive_autocracy","outliner_fleet_cloaked","pacifist","pause_button","paused","permanent_employment","pgdn","pgup","pharma_state","phototrophic","physics","planet","planetsize","player_not_ready","player_ready","pleasure_seekers","pleasure_seekers_corporate","plus","plus_minus","political_power","politics","pompus_purists","pop","pop_modifier","pops","privatized_exploration","prospectorium","protectorate","psychological_infertility","purity","pyroclastic","pyrolatry","radiotrophic","rare_crystals","reanimators","regulatory_node","relentless_industrialists","relentless_industrialists_megacorp","repair","research","resource_astral_threads","resource_minor_artifacts","resource_time","resource_time_grey","resource_unity","resource_unity_grey","return","risk","robot_aquatic","ruler","scavengers","scavengers_megacorp","scholarium","science","science_ship","science_ship_automate_exploration","science_ship_map","science_ship_survey","scientist","scintillating","scion","scorched_earth","secret_societies","secret_societies_corporate","sector","sector_capital","seed_pod","selective_kinship","shell_slag","shift","ship_category_crystalline_entity_rarity","ship_category_cutholoid_rarity","ship_category_space_amoeba_rarity","ship_category_tiyanki_rarity","ship_category_voidworm_rarity","ship_modifier","ship_size_behemoth","ship_size_colonizer","ship_size_constructor","ship_size_crystalline_entity","ship_size_cutholoid","ship_size_harbinger_stage_1","ship_size_harbinger_stage_2","ship_size_harbinger_stage_3","ship_size_mauler_stage_1","ship_size_mauler_stage_2","ship_size_mauler_stage_3","ship_size_military_1","ship_size_military_16","ship_size_military_1_torpedo","ship_size_military_2","ship_size_military_32","ship_size_military_4","ship_size_military_64","ship_size_military_8","ship_size_military_station","ship_size_science","ship_size_space_amoeba","ship_size_space_monster","ship_size_stinger_stage_1","ship_size_stinger_stage_2","ship_size_stinger_stage_3","ship_size_tiyanki","ship_size_transport","ship_size_voidworm","ship_size_voidworm_troika","ship_size_weaver_stage_1","ship_size_weaver_stage_2","ship_size_weaver_stage_3","ship_stats_armor","ship_stats_build_cost","ship_stats_build_time","ship_stats_cloaking_detection","ship_stats_cloaking_strength","ship_stats_damage","ship_stats_evasion","ship_stats_hitpoints","ship_stats_maintenance","ship_stats_piracy_supression","ship_stats_power","ship_stats_shield","ship_stats_special","ship_stats_speed","ship_xl_slot","shipclass_colonizer","shipclass_constructor","shipclass_military","shipclass_military_special","shipclass_military_station","shipclass_mining_station","shipclass_observation_station","shipclass_research_station","shipclass_science_ship","shipclass_starbase","shipclass_transport","situation_log","slavery","slot_component","social_friend_icon","society","sovereign_guardianship","sovereign_guardianship_corporate","sovereign_guardianship_hive","sovereign_guardianship_machine","space","space_creature","specimen_obtained","spiritualist","stability","stargazers","statecraft","storm_callers","storm_callers_megacorp","storm_forecast_map","storm_forecast_map_small","strategic_resource","subterfuge","superstitious_beliefs","superstitious_beliefs_corporate","synthetic_age","synthetic_evolution","system","systems","tab","tankbound","tankbound_corporate","the_flesh_is_weak","time","toxic_baths","toxic_baths_hive","toxic_baths_machine","toxic_baths_megacorp","trade_protection","trade_value","traditions","tributary","trigger_no","trigger_yes","twisted_experimenters","twisted_experimenters_corporate","twisted_experimenters_hive_mind","unbreakable_resolve","unity","universal_transactions","unyielding","upgrade","upgrade_ship","vassal","venerable_scientist","virtuality","void_hive","voidborn","volatile_excretions","volatile_motes","weather_control","world_forgers","xeno_compatibility","xenophile","xenophobe","zone","zro"]}